convoc/__init__.py
convoc/_version.py
convoc/converter/__init__.py
convoc/converter/csv2dir.py
convoc/converter/dir2csv.py
convoc/files/properties.py
convoc/files/validate.py
convoc/tools/exception.py
convoc/tools/log.py
exsample/exsample-csv2dir.py
exsample/exsample-dir2csv.py
convoc-0.0.1.dist-info/LICENSE
convoc-0.0.1.dist-info/METADATA
convoc-0.0.1.dist-info/WHEEL
convoc-0.0.1.dist-info/top_level.txt
convoc-0.0.1.dist-info/RECORD
