Metadata-Version: 2.1
Name: convoc
Version: 0.0.1
Summary: Package to convert csv and directories to each other.
Author-email: Hayato Sonokawa <hsono10n1@gmail.com>
Project-URL: Homepage, https://gitlab.com/hsono57/convoc
Project-URL: Bug Tracker, https://gitlab.com/hsono57/convocissues
Classifier: Programming Language :: Python :: 3
Classifier: License :: OSI Approved :: MIT License
Classifier: Operating System :: OS Independent
Requires-Python: >=3.8
License-File: LICENSE
